spyrate-0.1.5.dist-info/top_level.txt
spyrate-0.1.5.dist-info/RECORD
spyrate-0.1.5.dist-info/METADATA
spyrate-0.1.5.dist-info/WHEEL
spyrate/_rte_wrapper_double_precision.cpython-36m-x86_64-linux-gnu.so
spyrate/__build.py
spyrate/spyrate.py
spyrate/__init__.py
spyrate/.libs/libgfortran-ed201abd.so.3.0.0
spyrate/rte/rte_interface.py
spyrate/rte/rte_api.py
spyrate/rte/__init__.py
spyrate/rte/__pycache__/rte_interface.cpython-36.pyc
spyrate/rte/__pycache__/__init__.cpython-36.pyc
spyrate/rte/__pycache__/rte_api.cpython-36.pyc
spyrate/_lib/rte_wrapper.h
spyrate/_lib/Makefile
