Metadata-Version: 2.1
Name: spyrate
Version: 0.1.5
Summary: Python bindings to the Radiative Transfer for Energetics library
Home-page: https://github.com/JoyMonteiro/spyrate
Author: Joy Merwin Monteiro
Author-email: joy.merwin@gmail.com
License: BSD license
Keywords: spyrate
Platform: UNKNOWN
Classifier: Development Status :: 2 - Pre-Alpha
Classifier: Intended Audience :: Developers
Classifier: License :: OSI Approved :: BSD License
Classifier: Natural Language :: English
Classifier: Programming Language :: Python :: 3
Classifier: Programming Language :: Python :: 3.6
Classifier: Programming Language :: Python :: 3.7
Requires-Dist: cffi (>=1.12.3)
Requires-Dist: numpy (>=1.16.0)
